trackable/__init__.py
trackable/exceptions.py
trackable/report.py
trackable/types.py
trackable-0.1.0.dist-info/WHEEL
trackable-0.1.0.dist-info/LICENSE
trackable-0.1.0.dist-info/METADATA
trackable-0.1.0.dist-info/RECORD
